{
  "type": "object",
  "$schema": "http://json-schema.org/draft-06/schema#",
  "description": "The Help To Save account details",
  "properties": {
    "goalAmount": {
      "type": "number",
      "description": "The amount that the user wants to save each month. This must be a number between 1 and the monthly savings limit (currently £50)",
      "examples": [
        21.50,
        45
      ]
    },
    "goalName": {
      "type": "string",
      "description": "The name of the savings goal (Decoded to UTF-8)",
      "examples": [
        "Savings Goal",
        "\\xF0\\x9F\\x8F\\xA1 New home"
      ]
    }
  },
  "required": [
    "goalAmount"
  ]
}